caracara_filters/__init__.py
caracara_filters/common/__init__.py
caracara_filters/common/constants.py
caracara_filters/common/regex.py
caracara_filters/common/templates.py
caracara_filters/dialects/__init__.py
caracara_filters/dialects/_base.py
caracara_filters/dialects/_merge.py
caracara_filters/dialects/hosts.py
caracara_filters/dialects/iocs.py
caracara_filters/dialects/prevention_policies.py
caracara_filters/dialects/response_policies.py
caracara_filters/dialects/rtr.py
caracara_filters/dialects/users.py
caracara_filters/fql.py
caracara_filters/transforms/__init__.py
caracara_filters/transforms/identity.py
caracara_filters/transforms/relative_timestamp.py
caracara_filters/transforms/yes_no.py
caracara_filters/validators/__init__.py
caracara_filters/validators/boolean.py
caracara_filters/validators/identity.py
caracara_filters/validators/options.py
caracara_filters/validators/relative_timestamp.py
caracara_filters-1.1.0.dist-info/LICENSE
caracara_filters-1.1.0.dist-info/METADATA
caracara_filters-1.1.0.dist-info/WHEEL
caracara_filters-1.1.0.dist-info/RECORD
