Metadata-Version: 2.3
Name: caracara-filters
Version: 1.1.0
Summary: FQL generation engine for Caracara
License: MIT
Keywords: api,crowdstrike,falcon-platform,fql,query-language,sdk
Author: Chris Hammond
Author-email: chris.hammond@crowdstrike.com
Requires-Python: >=3.8.2,<4.0.0
Classifier: Intended Audience :: Developers
Classifier: License :: OSI Approved :: MIT License
Classifier: Natural Language :: English
Classifier: Operating System :: MacOS
Classifier: Operating System :: Microsoft :: Windows
Classifier: Operating System :: POSIX :: Linux
Classifier: Programming Language :: Python :: 3
Classifier: Programming Language :: Python :: 3.9
Classifier: Programming Language :: Python :: 3.10
Classifier: Programming Language :: Python :: 3.11
Classifier: Programming Language :: Python :: 3.12
Classifier: Programming Language :: Python :: 3.13
Classifier: Programming Language :: Python :: 3 :: Only
Classifier: Topic :: Security
Classifier: Topic :: Software Development :: Libraries
Classifier: Topic :: Text Processing :: Filters
Project-URL: Repository, https://github.com/CrowdStrike/caracara-filters
